pySeqAlign.cpython-36m-i386-linux-gnu.so
acoss/_version.py
acoss/coverid.py
acoss/features.py
acoss/extractors.py
acoss/utils.py
acoss/__init__.py
acoss/statistics/song_structure.py
acoss/statistics/onset_timing.py
acoss/statistics/__init__.py
acoss/statistics/cover_stats.py
acoss/benchmark/ftm2d.py
acoss/benchmark/simple_silva.py
acoss/benchmark/algorithm_template.py
acoss/benchmark/rqa_serra09.py
acoss/benchmark/earlyfusion_traile.py
acoss/benchmark/latefusion_chen.py
acoss/benchmark/__init__.py
acoss/benchmark/utils/__init__.py
acoss/benchmark/utils/similarity_fusion.py
acoss/benchmark/utils/cross_recurrence.py
acoss/benchmark/utils/alignment_tools/__init__.py
acoss-0.0.1.dist-info/top_level.txt
acoss-0.0.1.dist-info/RECORD
acoss-0.0.1.dist-info/METADATA
acoss-0.0.1.dist-info/WHEEL
