Metadata-Version: 2.1
Name: acoss
Version: 0.0.1
Summary: Audio Cover Song Suite (acoss): A benchmarking suite for cover song identification tasks
Home-page: https://github.com/furkanyesiler/acoss
Author: Albin Correya, Furkan Yesiler, Chris Traile, Philip Tovstogan, and Diego Silva
Author-email: albin.correya@upf.edu
License: AGPL3.0
Project-URL: Source, https://github.com/furkanyesiler/acoss
Project-URL: Tracker, https://github.com/furkanyesiler/acoss/issues
Keywords: audio music dsp musicinformationretireval coversongidentification
Platform: UNKNOWN
Classifier: Development Status :: 3 - Alpha
Classifier: License :: OSI Approved :: GNU Affero General Public License v3
Classifier: Intended Audience :: Developers
Classifier: Intended Audience :: Science/Research
Classifier: Topic :: Multimedia :: Sound/Audio :: Analysis
Classifier: Programming Language :: Python :: 3.5
Classifier: Programming Language :: Python :: 3.6
Provides-Extra: tests
Provides-Extra: docs
Requires-Dist: madmom
Requires-Dist: numpy (>=1.16.5)
Requires-Dist: pandas
Requires-Dist: scipy (==1.2.1)
Requires-Dist: scikit-learn (==0.19.2)
Requires-Dist: deepdish
Requires-Dist: essentia
Provides-Extra: docs
Provides-Extra: tests
